andrew_anderson_utils/__init__.py
andrew_anderson_utils/dbquery.py
andrew_anderson_utils/session_protocol.py
andrew_anderson_utils/x_structs.py
andrew_anderson_utils-0.3.1.dist-info/LICENSE
andrew_anderson_utils-0.3.1.dist-info/METADATA
andrew_anderson_utils-0.3.1.dist-info/WHEEL
andrew_anderson_utils-0.3.1.dist-info/top_level.txt
andrew_anderson_utils-0.3.1.dist-info/RECORD
